Metadata-Version: 1.1
Name: lcom
Version: 0.1.0
Summary: Lack of cohesion of methods metric
Home-page: https://github.com/potfur/lcom
Author: Michal Wachowski
Author-email: wachowski.michal@gmail.com
License: UNKNOWN
Download-URL: https://github.com/potfur/lcom/archive/0.1.0.tar.gz
Keywords: cohesion,code metrics,code quality,lcom,lcom4
Platform: UNKNOWN
Classifier: Intended Audience :: Developers
Classifier: Intended Audience :: Education
Classifier: Operating System :: OS Independent
Classifier: Programming Language :: Python :: 2.7
Classifier: Programming Language :: Python :: 3
Classifier: License :: OSI Approved :: MIT License
